f5_tts/api.py
f5_tts/socket_client.py
f5_tts/socket_server.py
f5_tts/configs/E2TTS_Base.yaml
f5_tts/configs/E2TTS_Small.yaml
f5_tts/configs/F5TTS_Base.yaml
f5_tts/configs/F5TTS_Small.yaml
f5_tts/configs/F5TTS_v1_Base.yaml
f5_tts/eval/README.md
f5_tts/eval/ecapa_tdnn.py
f5_tts/eval/eval_infer_batch.py
f5_tts/eval/eval_infer_batch.sh
f5_tts/eval/eval_infer_batch_example.sh
f5_tts/eval/eval_librispeech_test_clean.py
f5_tts/eval/eval_seedtts_testset.py
f5_tts/eval/eval_utmos.py
f5_tts/eval/utils_eval.py
f5_tts/infer/README.md
f5_tts/infer/SHARED.md
f5_tts/infer/infer_cli.py
f5_tts/infer/infer_gradio.py
f5_tts/infer/speech_edit.py
f5_tts/infer/utils_infer.py
f5_tts/infer/examples/vocab.txt
f5_tts/infer/examples/basic/basic.toml
f5_tts/infer/examples/basic/basic_ref_en.wav
f5_tts/infer/examples/basic/basic_ref_zh.wav
f5_tts/infer/examples/multi/country.flac
f5_tts/infer/examples/multi/main.flac
f5_tts/infer/examples/multi/story.toml
f5_tts/infer/examples/multi/story.txt
f5_tts/infer/examples/multi/town.flac
f5_tts/model/__init__.py
f5_tts/model/cfm.py
f5_tts/model/dataset.py
f5_tts/model/modules.py
f5_tts/model/trainer.py
f5_tts/model/utils.py
f5_tts/model/backbones/README.md
f5_tts/model/backbones/dit.py
f5_tts/model/backbones/mmdit.py
f5_tts/model/backbones/unett.py
f5_tts/runtime/triton_trtllm/.gitignore
f5_tts/runtime/triton_trtllm/Dockerfile.server
f5_tts/runtime/triton_trtllm/README.md
f5_tts/runtime/triton_trtllm/benchmark.py
f5_tts/runtime/triton_trtllm/client_grpc.py
f5_tts/runtime/triton_trtllm/client_http.py
f5_tts/runtime/triton_trtllm/docker-compose.yml
f5_tts/runtime/triton_trtllm/run.sh
f5_tts/runtime/triton_trtllm/model_repo_f5_tts/f5_tts/config.pbtxt
f5_tts/runtime/triton_trtllm/model_repo_f5_tts/f5_tts/1/f5_tts_trtllm.py
f5_tts/runtime/triton_trtllm/model_repo_f5_tts/f5_tts/1/model.py
f5_tts/runtime/triton_trtllm/model_repo_f5_tts/vocoder/config.pbtxt
f5_tts/runtime/triton_trtllm/model_repo_f5_tts/vocoder/1/.gitkeep
f5_tts-1.1.12.dist-info/licenses/LICENSE
f5_tts-1.1.12.dist-info/METADATA
f5_tts-1.1.12.dist-info/WHEEL
f5_tts-1.1.12.dist-info/entry_points.txt
f5_tts-1.1.12.dist-info/top_level.txt
f5_tts-1.1.12.dist-info/RECORD
