Metadata-Version: 2.4
Name: f5-tts
Version: 1.1.12
Summary: F5-TTS: A Fairytaler that Fakes Fluent and Faithful Speech with Flow Matching
License: MIT License
Project-URL: Homepage, https://github.com/SWivid/F5-TTS
Classifier: License :: OSI Approved :: MIT License
Classifier: Operating System :: OS Independent
Classifier: Programming Language :: Python :: 3
License-File: LICENSE
Requires-Dist: accelerate>=0.33.0
Requires-Dist: bitsandbytes>0.37.0; platform_machine != "arm64" and platform_system != "Darwin"
Requires-Dist: cached_path
Requires-Dist: click
Requires-Dist: datasets
Requires-Dist: ema_pytorch>=0.5.2
Requires-Dist: gradio>=6.0.0
Requires-Dist: hydra-core>=1.3.0
Requires-Dist: librosa
Requires-Dist: matplotlib
Requires-Dist: numpy<=1.26.4; python_version <= "3.10"
Requires-Dist: pydantic<=2.10.6
Requires-Dist: pydub
Requires-Dist: pypinyin
Requires-Dist: rjieba
Requires-Dist: safetensors
Requires-Dist: soundfile
Requires-Dist: tomli
Requires-Dist: torch>=2.0.0
Requires-Dist: torchaudio>=2.0.0
Requires-Dist: torchcodec
Requires-Dist: torchdiffeq
Requires-Dist: tqdm>=4.65.0
Requires-Dist: transformers
Requires-Dist: transformers_stream_generator
Requires-Dist: unidecode
Requires-Dist: vocos
Requires-Dist: wandb
Requires-Dist: x_transformers>=1.31.14
Provides-Extra: eval
Requires-Dist: faster_whisper==0.10.1; extra == "eval"
Requires-Dist: funasr; extra == "eval"
Requires-Dist: jiwer; extra == "eval"
Requires-Dist: modelscope; extra == "eval"
Requires-Dist: zhconv; extra == "eval"
Requires-Dist: zhon; extra == "eval"
Dynamic: license-file
